src/__init__.py
src/chromedriver
src/facebook.py
tests/__init__.py
bootFacebookAccountCreator-1.16.0.dist-info/LICENSE.chromedriver
bootFacebookAccountCreator-1.16.0.dist-info/METADATA
bootFacebookAccountCreator-1.16.0.dist-info/WHEEL
bootFacebookAccountCreator-1.16.0.dist-info/top_level.txt
bootFacebookAccountCreator-1.16.0.dist-info/RECORD
