Metadata-Version: 2.1
Name: bootFacebookAccountCreator
Version: 1.16.0
Summary: UNKNOWN
Home-page: UNKNOWN
Author: milerlite
Author-email: UNKNOWN
License: UNKNOWN
Platform: UNKNOWN
Requires-Dist: Faker (==20.1.0)
Requires-Dist: Genderize (==0.3.1)
Requires-Dist: PySocks (==1.7.1)
Requires-Dist: SQLAlchemy (==2.0.23)
Requires-Dist: aiosqlite (==0.17.0)
Requires-Dist: async-timeout (==4.0.3)
Requires-Dist: asyncpg (==0.29.0)
Requires-Dist: attrs (==23.1.0)
Requires-Dist: certifi (==2023.11.17)
Requires-Dist: charset-normalizer (==3.3.2)
Requires-Dist: exceptiongroup (==1.2.0)
Requires-Dist: fake-useragent (==1.4.0)
Requires-Dist: greenlet (==3.0.2)
Requires-Dist: h11 (==0.14.0)
Requires-Dist: idna (==3.6)
Requires-Dist: importlib-resources (==6.1.1)
Requires-Dist: iso8601 (==1.1.0)
Requires-Dist: numpy (==1.26.2)
Requires-Dist: outcome (==1.3.0.post0)
Requires-Dist: packaging (==23.2)
Requires-Dist: pandas (==2.1.4)
Requires-Dist: psycopg-binary (==3.1.13)
Requires-Dist: psycopg-pool (==3.2.0)
Requires-Dist: psycopg2-binary (==2.9.9)
Requires-Dist: psycopg (==3.1.13)
Requires-Dist: pypika-tortoise (==0.1.6)
Requires-Dist: python-dateutil (==2.8.2)
Requires-Dist: python-dotenv (==1.0.0)
Requires-Dist: pytz (==2023.3.post1)
Requires-Dist: requests (==2.31.0)
Requires-Dist: selenium-stealth (==1.0.6)
Requires-Dist: selenium (==4.15.2)
Requires-Dist: six (==1.16.0)
Requires-Dist: sniffio (==1.3.0)
Requires-Dist: sortedcontainers (==2.4.0)
Requires-Dist: tortoise-orm (==0.20.0)
Requires-Dist: trio-websocket (==0.11.1)
Requires-Dist: trio (==0.23.1)
Requires-Dist: typing-extensions (==4.8.0)
Requires-Dist: tzdata (==2023.3)
Requires-Dist: undetected-chromedriver (==3.5.4)
Requires-Dist: urllib3 (==2.1.0)
Requires-Dist: useragent (==0.1.1)
Requires-Dist: webdriver-manager (==4.0.1)
Requires-Dist: websockets (==12.0)
Requires-Dist: wsproto (==1.2.0)
Requires-Dist: zipp (==3.17.0)
